[
  {
    "UserID": "Sponge Bob",
    "Workout": "Bicept + Triceps",
    "Past-exercise": [
      {
        "workout-name": "pullup",
        "sets": 3,
        "reps": 5
      },
      {
        "workout-name": "pushup",
        "sets": 3,
        "reps": 15
      }]
  },
  {
    "UserID": "Plankton",
    "Workout": "Leg Killer",
    "Past-exercise": [
      {
        "workout-name": "Leg Press",
        "sets": 3,
        "reps": 8,
        "weight": 400
      },
      {
        "workout-name": "Squats",
        "sets": 3,
        "reps": 10,
        "weight": 220
      }]
  },
  {
    "UserID": "Sandy",
    "Workout": "UpperBody",
    "Past-exercise": [
      {
        "workout-name": "benchpress",
        "sets": 3,
        "reps": 12,
        "weight": 110
      },
      {
        "workout-name": "hammer curls",
        "sets": 3,
        "reps": 15,
        "weight": 40
      }]
  }
]